setup.py
jwis/JWISHTMLParser.py
jwis/__init__.py
jwis/__main__.py
jwis/jwislib.py
jwis.egg-info/PKG-INFO
jwis.egg-info/SOURCES.txt
jwis.egg-info/dependency_links.txt
jwis.egg-info/entry_points.txt
jwis.egg-info/top_level.txt