Metadata-Version: 1.1
Name: jwis
Version: 0.2.0
Summary: Data downloader from Japan Water System Information
Home-page: https://github.org/i-kiwamu/jwis
Author: Kiwamu Ishikura
Author-email: ishikura.kiwamu@gmail.com
License: UNKNOWN
Keywords: download,hydrology,japan
Platform: UNKNOWN
Classifier: Programming Language :: Python
Classifier: Programming Language :: Python :: 2.7
Classifier: Programming Language :: Python :: 3.3
Classifier: Programming Language :: Python :: 3.4
Classifier: Programming Language :: Python :: 3.5
Classifier: Development Status :: 4 - Beta
Classifier: Environment :: Console
Classifier: Intended Audience :: End Users/Desktop
Classifier: Intended Audience :: Science/Research
Classifier: License :: OSI Approved :: GNU General Public License v3 (GPLv3)
Classifier: Natural Language :: Japanese
Classifier: Operating System :: OS Independent
Classifier: Topic :: Scientific/Engineering
Classifier: Topic :: Utilities
